CPCProt/__init__.py
CPCProt/collate_fn.py
CPCProt/dataset.py
CPCProt/evaluate.py
CPCProt/finetune.py
CPCProt/finetune_simple.py
CPCProt/pretrain.py
CPCProt/schedulers.py
CPCProt/tokenizer.py
CPCProt/utils.py
CPCProt/validation.py
CPCProt/model/__init__.py
CPCProt/model/autoregressor.py
CPCProt/model/base_config.py
CPCProt/model/cpcprot.py
CPCProt/model/critics.py
CPCProt/model/encoder.py
CPCProt/model/heads.py
CPCProt/model/losses.py
bio_embeddings_CPCProt-0.0.1.dist-info/METADATA
bio_embeddings_CPCProt-0.0.1.dist-info/WHEEL
bio_embeddings_CPCProt-0.0.1.dist-info/top_level.txt
bio_embeddings_CPCProt-0.0.1.dist-info/RECORD
