Metadata-Version: 2.1
Name: bio-embeddings-CPCProt
Version: 0.0.1
Summary: Parameter-efficient pretrained model for obtaining protein embeddings.
Home-page: UNKNOWN
Author: Amy Lu
Author-email: amyxlu@cs.toronto.edu
License: UNKNOWN
Platform: UNKNOWN
Classifier: Programming Language :: Python :: 3
Classifier: License :: OSI Approved :: MIT License
Classifier: Operating System :: POSIX :: Linux
Requires-Python: >=3.6
Requires-Dist: numpy (<2.0,>=1.19)
Requires-Dist: torch (<2.0,>=1.0)
Requires-Dist: lmdb (<2.0,>=1.0)
Requires-Dist: bio-embeddings-tape-proteins (<=1.0,>=0.4)
Requires-Dist: scipy (<2.0,>=1.5)
